fastapi_csrf_protect/__init__.py
fastapi_csrf_protect/core.py
fastapi_csrf_protect/csrf_config.py
fastapi_csrf_protect/exceptions.py
fastapi_csrf_protect/load_config.py
fastapi_csrf_protect/py.typed
fastapi_csrf_protect/flexible/__init__.py
fastapi_csrf_protect/flexible/core.py
fastapi_csrf_protect/flexible/csrf_config.py
fastapi_csrf_protect/flexible/load_config.py
fastapi_csrf_protect-1.0.6.dist-info/METADATA
fastapi_csrf_protect-1.0.6.dist-info/WHEEL
fastapi_csrf_protect-1.0.6.dist-info/licenses/LICENSE
fastapi_csrf_protect-1.0.6.dist-info/RECORD
