Metadata-Version: 2.4
Name: fastapi-csrf-protect
Version: 1.0.6
Summary: Stateless implementation of Cross-Site Request Forgery (XSRF) Protection by using Double Submit Cookie mitigation pattern
Author-email: Sitt Guruvanich <aekazitt+github@gmail.com>
License-Expression: MIT
License-File: LICENSE
Keywords: asynchronous,cross-site request forgery,csrf,fastapi,samesite,starlette,xsrf
Classifier: Environment :: Web Environment
Classifier: Framework :: AsyncIO
Classifier: Intended Audience :: Developers
Classifier: License :: OSI Approved :: MIT License
Classifier: Operating System :: OS Independent
Classifier: Programming Language :: Python :: 3
Classifier: Programming Language :: Python :: 3 :: Only
Classifier: Programming Language :: Python :: 3.9
Classifier: Programming Language :: Python :: 3.10
Classifier: Programming Language :: Python :: 3.11
Classifier: Programming Language :: Python :: 3.12
Classifier: Programming Language :: Python :: 3.13
Classifier: Programming Language :: Python :: 3.14
Classifier: Topic :: Internet :: WWW/HTTP :: Dynamic Content
Classifier: Topic :: Software Development :: Libraries :: Python Modules
Requires-Python: >=3.9
Requires-Dist: itsdangerous<3.0.0,>=2.0.1
Requires-Dist: pydantic-settings>=2.0.0
Requires-Dist: pydantic>=2.0.0
Requires-Dist: starlette>=0
